LICENSE
MANIFEST.in
README.md
TODO.md
patu.py
setup.py
patu.egg-info/PKG-INFO
patu.egg-info/SOURCES.txt
patu.egg-info/dependency_links.txt
patu.egg-info/requires.txt
patu.egg-info/top_level.txt
scripts/patu
test/test.html
test/test.py
test/test_input.txt