Metadata-Version: 1.0
Name: patu
Version: 0.1
Summary: Patu is a small spider
Home-page: http://github.com/akrito/patu
Author: Alex Kritikos
Author-email: alex@8bitb.us
License: UNKNOWN
Platform: UNKNOWN
